PoliticoPolls.py
politico_polls_scraper-1.0.0.dist-info/LICENSE
politico_polls_scraper-1.0.0.dist-info/METADATA
politico_polls_scraper-1.0.0.dist-info/WHEEL
politico_polls_scraper-1.0.0.dist-info/top_level.txt
politico_polls_scraper-1.0.0.dist-info/RECORD
