Metadata-Version: 2.1
Name: politico-polls-scraper
Version: 1.0.0
Summary: Download polls data from Politico Polls.
Author-email: Robert Vamosi <vamosi.robert2@gmail.com>
License: MIT License
Project-URL: Homepage, https://github.com/VRobert123/politico_polls_scraper
Keywords: politico,polls,download,scraper,scraping,election,polls
Classifier: License :: OSI Approved :: MIT License
Classifier: Programming Language :: Python
Classifier: Programming Language :: Python :: 3
Requires-Python: >=3.9
License-File: LICENSE
Requires-Dist: pandas
Requires-Dist: selenium
Requires-Dist: datetime
Requires-Dist: bs4
